<annotation>
	<folder>frames</folder>
	<filename>frame_000297.jpg</filename>
	<path>D:\游戏\脚本\data\frames\frame_000297.jpg</path>
	<source>
		<database>Unknown</database>
	</source>
	<size>
		<width>1920</width>
		<height>1080</height>
		<depth>3</depth>
	</size>
	<segmented>0</segmented>
	<object>
		<name>求生者</name>
		<pose>Unspecified</pose>
		<truncated>0</truncated>
		<difficult>0</difficult>
		<bndbox>
			<xmin>1526</xmin>
			<ymin>319</ymin>
			<xmax>1684</xmax>
			<ymax>457</ymax>
		</bndbox>
	</object>
	<object>
		<name>木板</name>
		<pose>Unspecified</pose>
		<truncated>0</truncated>
		<difficult>0</difficult>
		<bndbox>
			<xmin>1618</xmin>
			<ymin>255</ymin>
			<xmax>1762</xmax>
			<ymax>491</ymax>
		</bndbox>
	</object>
</annotation>
